pretix_servicefees/__init__.py
pretix_servicefees/apps.py
pretix_servicefees/models.py
pretix_servicefees/signals.py
pretix_servicefees/urls.py
pretix_servicefees/views.py
pretix_servicefees/locale/django.pot
pretix_servicefees/locale/ar/LC_MESSAGES/django.mo
pretix_servicefees/locale/ar/LC_MESSAGES/django.po
pretix_servicefees/locale/ca/LC_MESSAGES/django.mo
pretix_servicefees/locale/ca/LC_MESSAGES/django.po
pretix_servicefees/locale/cs/LC_MESSAGES/django.mo
pretix_servicefees/locale/cs/LC_MESSAGES/django.po
pretix_servicefees/locale/da/LC_MESSAGES/django.mo
pretix_servicefees/locale/da/LC_MESSAGES/django.po
pretix_servicefees/locale/de/LC_MESSAGES/django.mo
pretix_servicefees/locale/de/LC_MESSAGES/django.po
pretix_servicefees/locale/de_Informal/.gitkeep
pretix_servicefees/locale/de_Informal/LC_MESSAGES/django.mo
pretix_servicefees/locale/de_Informal/LC_MESSAGES/django.po
pretix_servicefees/locale/el/LC_MESSAGES/django.mo
pretix_servicefees/locale/el/LC_MESSAGES/django.po
pretix_servicefees/locale/es/LC_MESSAGES/django.mo
pretix_servicefees/locale/es/LC_MESSAGES/django.po
pretix_servicefees/locale/fi/LC_MESSAGES/django.mo
pretix_servicefees/locale/fi/LC_MESSAGES/django.po
pretix_servicefees/locale/fr/LC_MESSAGES/django.mo
pretix_servicefees/locale/fr/LC_MESSAGES/django.po
pretix_servicefees/locale/hr/LC_MESSAGES/django.mo
pretix_servicefees/locale/hr/LC_MESSAGES/django.po
pretix_servicefees/locale/it/LC_MESSAGES/django.mo
pretix_servicefees/locale/it/LC_MESSAGES/django.po
pretix_servicefees/locale/ja/LC_MESSAGES/django.mo
pretix_servicefees/locale/ja/LC_MESSAGES/django.po
pretix_servicefees/locale/lv/LC_MESSAGES/django.mo
pretix_servicefees/locale/lv/LC_MESSAGES/django.po
pretix_servicefees/locale/nl/LC_MESSAGES/django.mo
pretix_servicefees/locale/nl/LC_MESSAGES/django.po
pretix_servicefees/locale/nl_Informal/LC_MESSAGES/django.mo
pretix_servicefees/locale/nl_Informal/LC_MESSAGES/django.po
pretix_servicefees/locale/pl/LC_MESSAGES/django.mo
pretix_servicefees-1.15.0.dist-info/licenses/LICENSE
pretix_servicefees-1.15.0.dist-info/METADATA
pretix_servicefees-1.15.0.dist-info/WHEEL
pretix_servicefees-1.15.0.dist-info/entry_points.txt
pretix_servicefees-1.15.0.dist-info/top_level.txt
pretix_servicefees-1.15.0.dist-info/RECORD
