Metadata-Version: 2.4
Name: pretix-servicefees
Version: 1.15.0
Summary: Allows you to impose a service fee on all non-free orders.
Author-email: pretix team <support@pretix.eu>
Maintainer-email: pretix team <support@pretix.eu>
License: Copyright 2018 Raphael Michel
Project-URL: homepage, https://github.com/pretix/pretix-servicefees
Keywords: pretix
Requires-Python: >=3.9
License-File: LICENSE
Dynamic: license-file
